steelseries/Example.py
steelseries/__init__.py
steelseries-0.3.1.dist-info/licenses/LICENSE.txt
steelseries-0.3.1.dist-info/METADATA
steelseries-0.3.1.dist-info/WHEEL
steelseries-0.3.1.dist-info/top_level.txt
steelseries-0.3.1.dist-info/RECORD
