Metadata-Version: 2.4
Name: steelseries
Version: 0.3.1
Summary: Simple Python SDK for the SteelSeries GameSense API
Author-email: NeoEmberArts <authoranimation@gmail.com>
License: MIT
Classifier: Programming Language :: Python :: 3
Classifier: Operating System :: Microsoft :: Windows
Classifier: License :: OSI Approved :: MIT License
Classifier: Intended Audience :: Developers
Classifier: Topic :: Games/Entertainment
Classifier: Topic :: Software Development :: Libraries :: Python Modules
Requires-Python: >=3.7
License-File: LICENSE.txt
Requires-Dist: requests
Dynamic: license-file
